happy_migrations/__init__.py
happy_migrations/__main__.py
happy_migrations/_data_classes.py
happy_migrations/_echo_msg.py
happy_migrations/_sql.py
happy_migrations/_templates.py
happy_migrations/_textual_app.py
happy_migrations/_utils.py
happy_migrations/sqlite_backend.py
happy_migrations/cli/__init__.py
happy_migrations/cli/demo.py
happy_migrations/cli/social.py
happy_migrations-0.0.5.dist-info/METADATA
happy_migrations-0.0.5.dist-info/WHEEL
happy_migrations-0.0.5.dist-info/entry_points.txt
happy_migrations-0.0.5.dist-info/licenses/LICENSE
happy_migrations-0.0.5.dist-info/RECORD
